turboml_bindings-0.1.4.dist-info/METADATA
turboml_bindings-0.1.4.dist-info/RECORD
turboml_bindings-0.1.4.dist-info/WHEEL
turboml_bindings.libs/libpqxx-7-3479aee5.9.so
turboml_bindings.libs/libabsl_hash-4463b3a2.so.2407.0.0
turboml_bindings.libs/libabsl_cordz_handle-8cbd77c8.so.2407.0.0
turboml_bindings.libs/libonnxruntime-ad444c76.so.1.18.1
turboml_bindings.libs/libuuid-b802d850.so.16.0.22
turboml_bindings.libs/libabsl_random_internal_platform-70791509.so.2407.0.0
turboml_bindings.libs/libabsl_demangle_rust-1c858f10.so.2407.0.0
turboml_bindings.libs/libicudata-850e775f.so.74.2
turboml_bindings.libs/libre2-cf91ede4.so.11.0.0
turboml_bindings.libs/libllama-79a05e2c.so
turboml_bindings.libs/libabsl_status-16e8dbd2.so.2407.0.0
turboml_bindings.libs/libblas-f88e6662.so.3
turboml_bindings.libs/libgrpc-b0ef5738.so.44.0.0
turboml_bindings.libs/libabsl_statusor-1590405d.so.2407.0.0
turboml_bindings.libs/libabsl_cord_internal-1dd3a2d7.so.2407.0.0
turboml_bindings.libs/libabsl_log_initialize-e5542576.so.2407.0.0
turboml_bindings.libs/libabsl_str_format_internal-68fa09e6.so.2407.0.0
turboml_bindings.libs/libabsl_log_internal_globals-94524f42.so.2407.0.0
turboml_bindings.libs/libabsl_log_internal_conditions-36c20e62.so.2407.0.0
turboml_bindings.libs/libabsl_random_internal_randen_slow-84ceb110.so.2407.0.0
turboml_bindings.libs/libprotobuf-lite-217a0cf2.so.25.5.0
turboml_bindings.libs/libabsl_throw_delegate-7becb9ba.so.2407.0.0
turboml_bindings.libs/libabsl_log_internal_check_op-e0c603bd.so.2407.0.0
turboml_bindings.libs/libabsl_bad_variant_access-57ffd9c1.so.2407.0.0
turboml_bindings.libs/libboost_serialization-56b43acf.so.1.84.0
turboml_bindings.libs/libupb_mini_descriptor_lib-bd9bab6f.so.44.0.0
turboml_bindings.libs/libabsl_random_internal_pool_urbg-e9fd7569.so.2407.0.0
turboml_bindings.libs/libidn2-db2d5489.so.0.4.0
turboml_bindings.libs/libssh2-23d0f2bb.so.1.0.1
turboml_bindings.libs/libggml-be3da553.so
turboml_bindings.libs/libgoogle_cloud_cpp_type_decimal_protos-19f853b5.so.2.29.0
turboml_bindings.libs/libabsl_strerror-27ac5a54.so.2407.0.0
