Metadata-Version: 2.1
Name: turboml_bindings
Version: 0.1.4
Summary: C++ extension modules for TurboML
Author: TurboML, Inc.
Author-email: hello@turboml.com
Requires-Python: >=3.10,<4.0
Classifier: Programming Language :: Python :: 3
Classifier: Programming Language :: Python :: 3.10
Classifier: Programming Language :: Python :: 3.11
Classifier: Programming Language :: Python :: 3.12
Classifier: Programming Language :: Python :: 3.13
